lokii/__init__.py
lokii/lokii.py
lokii/table.py
lokii/utils.py
tests/__init__.py
tests/test_lokii.py
tests/test_table.py
lokii-0.1.3.dist-info/LICENSE
lokii-0.1.3.dist-info/METADATA
lokii-0.1.3.dist-info/WHEEL
lokii-0.1.3.dist-info/top_level.txt
lokii-0.1.3.dist-info/RECORD
