Metadata-Version: 2.1
Name: lokii
Version: 0.1.3
Summary: CSV dataset generator
Home-page: http://path-to-my-packagename
Author: Package Author
Author-email: you@youremail.com
License: MIT License
Keywords: boilerplate package
Platform: UNKNOWN
Classifier: Development Status :: 3 - Alpha
Classifier: Intended Audience :: Developers
Classifier: Topic :: Software Development
Classifier: License :: OSI Approved :: MIT License
Classifier: Programming Language :: Python :: 3
Classifier: Programming Language :: Python :: 3.4
Classifier: Programming Language :: Python :: 3.5
Classifier: Programming Language :: Python :: 3.6
Classifier: Programming Language :: Python :: 3.8
Requires-Dist: pathos
Requires-Dist: pandas
